plone.contentrules-3.0.2-py3.13-nspkg.pth
plone/contentrules/README.rst
plone/contentrules/__init__.py
plone/contentrules/configure.zcml
plone/contentrules/meta.zcml
plone/contentrules/tests.py
plone/contentrules/zcml.rst
plone/contentrules/engine/__init__.py
plone/contentrules/engine/assignments.py
plone/contentrules/engine/configure.zcml
plone/contentrules/engine/executor.py
plone/contentrules/engine/interfaces.py
plone/contentrules/engine/storage.py
plone/contentrules/engine/utils.py
plone/contentrules/rule/__init__.py
plone/contentrules/rule/configure.zcml
plone/contentrules/rule/element.py
plone/contentrules/rule/eventvocab.py
plone/contentrules/rule/interfaces.py
plone/contentrules/rule/meta.zcml
plone/contentrules/rule/metaconfigure.py
plone/contentrules/rule/metadirectives.py
plone/contentrules/rule/rule.py
plone/contentrules/rule/tests/__init__.py
plone/contentrules/rule/tests/elements.py
plone_contentrules-3.0.2.dist-info/METADATA
plone_contentrules-3.0.2.dist-info/WHEEL
plone_contentrules-3.0.2.dist-info/namespace_packages.txt
plone_contentrules-3.0.2.dist-info/top_level.txt
plone_contentrules-3.0.2.dist-info/RECORD
